{
  "releases": [
    {
      "name": "N0VA_19.txt",
      "type": "ASCII",
      "date": "22/06/2019",
      "url": "collyviewer.html?collyname=nkx-nova19.txt&extendedcolumns=40&displaymode=ced"
    },
    {
      "name": "nkx-versus9-votesheet",
      "type": "ASCII",
      "date": "06/07/2019",
      "url": "collyviewer.html?collyname=nkx-versus9-votesheet.txt&displaymode=ced"
    },
    {
      "name": "nkx-evoke2o19.txt",
      "type": "ASCII",
      "date": "18/08/2019",
      "url": "collyviewer.html?collyname=nkx-evoke2o19.txt&displaymode=ced"
    },
    {
      "name": "DLine_GeoMetriX.ans",
      "type": "ANSI",
      "date": "04/10/2019",
      "url": "collyviewer.html?collyname=DLine_GeoMetriX.ans.txt&linelength=120"
    },
    {
      "name": "nkx-rev2o2o.txt",
      "type": "ASCII",
      "date": "11/04/2020",
      "url": "collyviewer.html?collyname=nkx-rev2o2o.txt&extendedcolumns=25&displaymode=ced"
    },
    {
      "name": "nOVA-pARTY-nETWORK.ans",
      "type": "ANSI",
      "date": "21/06/2020",
      "url": "collyviewer.html?collyname=nOVA-pARTY-nETWORK.ans&linelength=100"
    },
    {
      "name": "goodbye_solskogen.ans",
      "type": "ANSI",
      "date": "11/07/2020",
      "url": "collyviewer.html?collyname=goodbye_solskogen.ans"
    },
    {
      "name": "Solskogen 2020 Logo",
      "type": "GFXTRO",
      "date": "11/07/2020",
      "url": "solskogen2020gfxtro/"
    },
    {
      "name": "b1nary_ra1n.ans",
      "type": "ANSI",
      "date": "15/08/2020",
      "url": "collyviewer.html?collyname=b1nary_ra1n.ans&linelength=80"
    },
    {
      "name": "NKXmastro 2o2o",
      "type": "INTRO",
      "date": "18/12/2020",
      "url": "https://code.obviousdisaster.dev/nkxmastro"
    },
    {
      "name": "mERRY fORNDATA x-MAS",
      "type": "ANSI",
      "date": "19/12/2020",
      "url": "collyviewer.html?collyname=nkx_merry_fdata_xmas.ans"
    },
    {
      "name": "nkx_together.ans",
      "type": "ANSI",
      "date": "03/04/2021",
      "url": "collyviewer.html?collyname=nkx_together.ans&disableblink=true"
    },
    {
      "name": "nkx_txt_art_4ever.txt",
      "type": "ASCII",
      "date": "04/09/2021",
      "url": "collyviewer.html?collyname=nkx_txt_art_4ever.txt&extendedcolumns=40&displaymode=ced"
    },
    {
      "name": "nkx_dline_reunited.ans",
      "type": "ANSI",
      "date": "09/10/2021",
      "url": "collyviewer.html?collyname=nkx_dline_reunited.ans"
    },
    {
      "name": "fzn_ansi_logo_colly_1.ans",
      "type": "ANSI",
      "date": "16/04/2022",
      "url": "collyviewer.html?collyname=fzn_ansi_logo_colly_1.ans"
    },
    {
      "name": "nkx_welcome_to_the_jungle.ans",
      "type": "ANSI",
      "date": "22/07/2022",
      "url": "collyviewer.html?collyname=nkx_welcome_to_the_jungle.ans"
    },
    {
      "name": "nkx_geo_vector_overload.ans",
      "type": "ANSI",
      "date": "06/08/2022",
      "url": "collyviewer.html?collyname=nkx_geo_vector_overload.ans"
    },
    {
      "name": "nkx_midnight_in_bud.ans",
      "type": "ANSI",
      "date": "13/08/2022",
      "url": "collyviewer.html?collyname=nkx_midnight_in_bud.ans&linelength=120"
    },
    {
      "name": "nkx_kung_fu_afro_twins.txt",
      "type": "ASCII",
      "date": "01/10/2022",
      "url": "collyviewer.html?collyname=nkx_kung_fu_afro_twins.txt&extendedcolumns=30&displaymode=ced"
    },
    {
      "name": "nkx_splash_party.ans",
      "type": "ANSI",
      "date": "19/11/2022",
      "url": "collyviewer.html?collyname=nkx_splash_party.ans"
    },
    {
      "name": "SPAG2.txt",
      "type": "ASCII",
      "date": "23/03/2023",
      "url": "collyviewer.html?collyname=SPAG2.txt&extendedcolumns=13&displaymode=ced"
    },
    {
      "name": "SPAG2.ans",
      "type": "ANSI",
      "date": "23/03/2023",
      "url": "collyviewer.html?collyname=SPAG2.ans"
    },
    {
      "name": "nkx_bk_2_da_ewerk.txt",
      "type": "ASCII",
      "date": "09/04/2023",
      "url": "collyviewer.html?collyname=nkx_bk_2_da_ewerk.txt&extendedcolumns=1&displaymode=ced"
    },
    {
      "name": "k33pin'-iT-oldskoOL.ans",
      "type": "ANSI",
      "date": "24/06/2023",
      "url": "collyviewer.html?collyname=k33pin'-iT-oldskoOL.ans"
    },
    {
      "name": "Metal-Impact-BBS-LoGO-PacK.ans",
      "type": "ANSI",
      "date": "24/07/2023",
      "url": "collyviewer.html?collyname=Metal-Impact-BBS-LoGO-PacK.ans"
    },
    {
      "name": "moto_pow3r.ans",
      "type": "ANSI",
      "date": "29/07/2023",
      "url": "collyviewer.html?collyname=moto_pow3r.ans"
    },
    {
      "name": "fzn-flash-dance-party.txt",
      "type": "ASCII",
      "date": "28/10/2023",
      "url": "collyviewer.html?collyname=fzn-flash-dance-party.txt&displaymode=ced"
    },
    {
      "name": "R32BBS_Xmas_Logo_Pack.ans",
      "type": "ANSI",
      "date": "06/12/2023",
      "url": "collyviewer.html?collyname=R32BBS_Xmas_Logo_Pack.ans"
    },
    {
      "name": "R32-BBS-bABY.ans",
      "type": "ANSI",
      "date": "15/06/2024",
      "url": "collyviewer.html?collyname=R32-BBS-bABY.ans"
    },
    {
      "name": "retro32-ansi.ans",
      "type": "ANSI",
      "date": "25/06/2025",
      "url": "collyviewer.html?collyname=retro32-ansi.ans&font=80x25&linelength=220"
    },
    {
      "name": "fzn-tboo-nova25.txt",
      "type": "ASCII",
      "date": "25/06/2025",
      "url": "collyviewer.html?collyname=fzn-tboo-nova25.txt"
    },
    {
      "name": "fzn-tboo.txt",
      "type": "ASCII",
      "date": "25/06/2025",
      "url": "collyviewer.html?collyname=fzn-tboo.txt"
    },
    {
      "name": "FP-DiGi-ArTS.txt",
      "type": "ASCII",
      "date": "18/10/2025",
      "url": "collyviewer.html?collyname=FP-DiGi-ArTS.txt&displaymode=ced"
    }
  ]
}